OASYS1_XOPPY-1.0.39-py3.6-nspkg.pth
OASYS1_XOPPY-1.0.39.dist-info/DESCRIPTION.rst
OASYS1_XOPPY-1.0.39.dist-info/METADATA
OASYS1_XOPPY-1.0.39.dist-info/RECORD
OASYS1_XOPPY-1.0.39.dist-info/WHEEL
OASYS1_XOPPY-1.0.39.dist-info/entry_points.txt
OASYS1_XOPPY-1.0.39.dist-info/metadata.json
OASYS1_XOPPY-1.0.39.dist-info/namespace_packages.txt
OASYS1_XOPPY-1.0.39.dist-info/top_level.txt
orangecontrib/xoppy/menu/__init__.py
orangecontrib/xoppy/menu/xoppy_tools_menu.py
orangecontrib/xoppy/util/__init__.py
orangecontrib/xoppy/util/fit_gaussian2d.py
orangecontrib/xoppy/util/srundplug.py
orangecontrib/xoppy/util/xoppy_bm_wiggler.py
orangecontrib/xoppy/util/xoppy_pymca_tools.py
orangecontrib/xoppy/util/xoppy_undulators.py
orangecontrib/xoppy/util/xoppy_util.py
orangecontrib/xoppy/util/xoppy_xraylib_util.py
orangecontrib/xoppy/util/bin/darwin/compliance
orangecontrib/xoppy/util/bin/darwin/diff_pat
orangecontrib/xoppy/util/bin/darwin/inpro
orangecontrib/xoppy/util/bin/darwin/mlayer
orangecontrib/xoppy/util/bin/darwin/tasmip
orangecontrib/xoppy/util/bin/darwin/tc
orangecontrib/xoppy/util/bin/darwin/urgent
orangecontrib/xoppy/util/bin/darwin/us
orangecontrib/xoppy/util/bin/darwin/ws
orangecontrib/xoppy/util/bin/darwin/xcom
orangecontrib/xoppy/util/bin/darwin/xpowder_fml
orangecontrib/xoppy/util/bin/darwin/xtubes
orangecontrib/xoppy/util/bin/linux/compliance
orangecontrib/xoppy/util/bin/linux/diff_pat
orangecontrib/xoppy/util/bin/linux/inpro
orangecontrib/xoppy/util/bin/linux/mlayer
orangecontrib/xoppy/util/bin/linux/tasmip
orangecontrib/xoppy/util/bin/linux/tc
orangecontrib/xoppy/util/bin/linux/urgent
orangecontrib/xoppy/util/bin/linux/us
orangecontrib/xoppy/util/bin/linux/ws
orangecontrib/xoppy/util/bin/linux/xcom
orangecontrib/xoppy/util/bin/linux/xpowder_fml
orangecontrib/xoppy/util/bin/linux/xtubes
orangecontrib/xoppy/util/bin/windows/compliance.exe
orangecontrib/xoppy/util/bin/windows/cryst_ml.exe
orangecontrib/xoppy/util/bin/windows/cryst_pp.exe
orangecontrib/xoppy/util/bin/windows/cryst_tt.exe
orangecontrib/xoppy/util/bin/windows/cryst_za.exe
orangecontrib/xoppy/util/bin/windows/diff_pat.exe
orangecontrib/xoppy/util/bin/windows/inpro.exe
orangecontrib/xoppy/util/bin/windows/mlayer.exe
orangecontrib/xoppy/util/bin/windows/tasmip.exe
