Metadata-Version: 2.0
Name: OASYS1-XOPPY
Version: 1.0.39
Summary: XOPPY: XOP (X-ray oriented programs) in Python
Home-page: https://github.com/oasys-kit/XOPPY
Author: Manuel Sanchez del Rio, Luca Rebuffi, and Bioinformatics Laboratory, FRI UL
Author-email: srio@esrf.eu, lrebuffi@anl.gov
License: GPLv3
Download-URL: https://github.com/oasys-kit/XOPPY
Keywords: X-ray optics,simulator,oasys1
Platform: UNKNOWN
Classifier: Development Status :: 5 - Production/Stable
Classifier: Environment :: X11 Applications :: Qt
Classifier: Environment :: Console
Classifier: Environment :: Plugins
Classifier: Programming Language :: Python :: 3
Classifier: Intended Audience :: Science/Research
Requires-Dist: oasys1 (>=1.1.41)
Requires-Dist: oasys1-srwlib
Requires-Dist: pySRU
